huggingface_togetherai/__init__.py
huggingface_togetherai/chat_models.py
huggingface_togetherai/py.typed
huggingface_togetherai/version.py
huggingface_togetherai-1.1.2.dist-info/LICENSE
huggingface_togetherai-1.1.2.dist-info/METADATA
huggingface_togetherai-1.1.2.dist-info/WHEEL
huggingface_togetherai-1.1.2.dist-info/top_level.txt
huggingface_togetherai-1.1.2.dist-info/RECORD
