Metadata-Version: 2.2
Name: huggingface-togetherai
Version: 1.1.2
Summary: Add your description here
Requires-Python: <3.13,>=3.10
License-File: LICENSE
Requires-Dist: langchain>=0.3.18
Requires-Dist: langchain-community>=0.3.17
Requires-Dist: openai>=1.61.1
